{
  "key": "plugin_content_manager_configuration_content_types::api::about.about",
  "value": {
    "uid": "api::about.about",
    "settings": {
      "bulkable": true,
      "filterable": true,
      "searchable": true,
      "pageSize": 10,
      "mainField": "id",
      "defaultSortBy": "id",
      "defaultSortOrder": "ASC"
    },
    "metadatas": {
      "id": {
        "edit": {},
        "list": {
          "label": "id",
          "searchable": true,
          "sortable": true
        }
      },
      "hero": {
        "edit": {
          "label": "hero",
          "description": "",
          "placeholder": "",
          "visible": true,
          "editable": true
        },
        "list": {
          "label": "hero",
          "searchable": false,
          "sortable": false
        }
      },
      "team": {
        "edit": {
          "label": "team",
          "description": "",
          "placeholder": "",
          "visible": true,
          "editable": true
        },
        "list": {
          "label": "team",
          "searchable": false,
          "sortable": false
        }
      },
      "story": {
        "edit": {
          "label": "story",
          "description": "",
          "placeholder": "",
          "visible": true,
          "editable": true
        },
        "list": {
          "label": "story",
          "searchable": false,
          "sortable": false
        }
      },
      "core": {
        "edit": {
          "label": "core",
          "description": "",
          "placeholder": "",
          "visible": true,
          "editable": true
        },
        "list": {
          "label": "core",
          "searchable": false,
          "sortable": false
        }
      },
      "createdAt": {
        "edit": {
          "label": "createdAt",
          "description": "",
          "placeholder": "",
          "visible": false,
          "editable": true
        },
        "list": {
          "label": "createdAt",
          "searchable": true,
          "sortable": true
        }
      },
      "updatedAt": {
        "edit": {
          "label": "updatedAt",
          "description": "",
          "placeholder": "",
          "visible": false,
          "editable": true
        },
        "list": {
          "label": "updatedAt",
          "searchable": true,
          "sortable": true
        }
      },
      "createdBy": {
        "edit": {
          "label": "createdBy",
          "description": "",
          "placeholder": "",
          "visible": false,
          "editable": true,
          "mainField": "firstname"
        },
        "list": {
          "label": "createdBy",
          "searchable": true,
          "sortable": true
        }
      },
      "updatedBy": {
        "edit": {
          "label": "updatedBy",
          "description": "",
          "placeholder": "",
          "visible": false,
          "editable": true,
          "mainField": "firstname"
        },
        "list": {
          "label": "updatedBy",
          "searchable": true,
          "sortable": true
        }
      }
    },
    "layouts": {
      "list": [
        "id",
        "hero",
        "createdAt",
        "updatedAt"
      ],
      "edit": [
        [
          {
            "name": "hero",
            "size": 12
          }
        ],
        [
          {
            "name": "team",
            "size": 12
          }
        ],
        [
          {
            "name": "story",
            "size": 12
          }
        ],
        [
          {
            "name": "core",
            "size": 12
          }
        ]
      ]
    }
  },
  "type": "object",
  "environment": null,
  "tag": null
}